outguncsv/README.MD
outguncsv/__init__.py
outguncsv/requirements.txt
outguncsv/thirdparty.json
outguncsv-0.11.dist-info/LICENSE.rst
outguncsv-0.11.dist-info/METADATA
outguncsv-0.11.dist-info/WHEEL
outguncsv-0.11.dist-info/top_level.txt
outguncsv-0.11.dist-info/RECORD
