Metadata-Version: 2.1
Name: outguncsv
Version: 0.11
Summary: Finds the right CSV separator and excludes bad lines in corrupt CSV files
Home-page: https://github.com/hansalemaos/outguncsv
Author: Johannes Fischer
Author-email: <aulasparticularesdealemaosp@gmail.com>
License: MIT
Keywords: pandas,read_csv,corrupt,csv,numpy
Classifier: Development Status :: 4 - Beta
Classifier: Programming Language :: Python :: 3 :: Only
Classifier: Programming Language :: Python :: 3.10
Classifier: Topic :: Scientific/Engineering :: Visualization
Classifier: Topic :: Software Development :: Libraries :: Python Modules
Classifier: Topic :: Utilities
License-File: LICENSE.rst
Requires-Dist: pandas
Requires-Dist: regex
Requires-Dist: requests
Requires-Dist: tolerant-isinstance
